{"PREVALENCE_BY_GENDER_AGE_YEAR":{"TRELLIS_NAME":["70-79","50-59","20-29","30-39","10-19","60-69"],"SERIES_NAME":["FEMALE","FEMALE","FEMALE","FEMALE","MALE","MALE"],"X_CALENDAR_YEAR":[2019,2019,2019,2019,2019,2019],"Y_PREVALENCE_1000PP":[1.29462,1.0142,1.00134,1.62575,1.37741,1.35344]},"PREVALENCE_BY_MONTH":{"X_CALENDAR_MONTH":[201901,201904,201906,201907,201909],"Y_PREVALENCE_1000PP":[0.12,0.11,0.09,0.06,0.11]},"CONDITIONS_BY_TYPE":{"CONCEPT_NAME":"Claim","COUNT_VALUE":102},"AGE_AT_FIRST_DIAGNOSIS":{"CATEGORY":["FEMALE","MALE"],"MIN_VALUE":[2,3],"P10_VALUE":[19,14],"P25_VALUE":[28,24],"MEDIAN_VALUE":[41,51],"P75_VALUE":[64,68],"P90_VALUE":[75,71],"MAX_VALUE":[96,80]}}
