{"PREVALENCE_BY_GENDER_AGE_YEAR":{"TRELLIS_NAME":"70-79","SERIES_NAME":"FEMALE","X_CALENDAR_YEAR":2019,"Y_PREVALENCE_1000PP":1.10967},"PREVALENCE_BY_MONTH":{"X_CALENDAR_MONTH":[201902,201904,201910],"Y_PREVALENCE_1000PP":[0.07,0.06,0.07]},"CONDITIONS_BY_TYPE":{"CONCEPT_NAME":"Claim","COUNT_VALUE":68},"AGE_AT_FIRST_DIAGNOSIS":{"CATEGORY":["FEMALE","MALE"],"MIN_VALUE":[11,0],"P10_VALUE":[16,7],"P25_VALUE":[37,25],"MEDIAN_VALUE":[52,42],"P75_VALUE":[69,60],"P90_VALUE":[72,69],"MAX_VALUE":[79,90]}}
