{"PREVALENCE_BY_GENDER_AGE_YEAR":{"TRELLIS_NAME":["10-19","20-29","10-19","60-69","50-59","50-59","20-29","70-79"],"SERIES_NAME":["FEMALE","MALE","MALE","FEMALE","MALE","FEMALE","FEMALE","FEMALE"],"X_CALENDAR_YEAR":[2019,2019,2019,2019,2019,2019,2019,2019],"Y_PREVALENCE_1000PP":[1.31176,1.51668,1.37489,1.52207,1.02684,1.15892,0.99917,1.48258]},"PREVALENCE_BY_MONTH":{"X_CALENDAR_MONTH":[201901,201902,201904,201905,201906,201907,201908,201909,201910],"Y_PREVALENCE_1000PP":[0.1,0.08,0.1,0.06,0.07,0.09,0.07,0.1,0.13]},"PROCEDURE_FREQUENCY_DISTRIBUTION":{"Y_NUM_PERSONS":[0,0,0],"X_COUNT":[1,2,3]},"PROCEDURES_BY_TYPE":{"CONCEPT_NAME":"Claim","COUNT_VALUE":129},"AGE_AT_FIRST_OCCURRENCE":{"CATEGORY":["MALE","FEMALE"],"MIN_VALUE":[0,3],"P10_VALUE":[11,12],"P25_VALUE":[20,28],"MEDIAN_VALUE":[30,55],"P75_VALUE":[57,73],"P90_VALUE":[65,87],"MAX_VALUE":[89,99]}}
