{"PREVALENCE_BY_GENDER_AGE_YEAR":{"TRELLIS_NAME":["60-69","30-39","50-59","20-29","40-49"],"SERIES_NAME":["FEMALE","MALE","FEMALE","FEMALE","FEMALE"],"X_CALENDAR_YEAR":[2019,2019,2019,2019,2019],"Y_PREVALENCE_1000PP":[1.33181,1.18624,0.86919,1.49875,0.85653]},"PREVALENCE_BY_MONTH":{"X_CALENDAR_MONTH":[201904,201905,201907,201908,201909,201910,201911],"Y_PREVALENCE_1000PP":[0.06,0.06,0.09,0.06,0.07,0.1,0.07]},"PROCEDURE_FREQUENCY_DISTRIBUTION":{"Y_NUM_PERSONS":[0,0,0],"X_COUNT":[1,2,3]},"PROCEDURES_BY_TYPE":{"CONCEPT_NAME":"Claim","COUNT_VALUE":99},"AGE_AT_FIRST_OCCURRENCE":{"CATEGORY":["MALE","FEMALE"],"MIN_VALUE":[4,12],"P10_VALUE":[16,20],"P25_VALUE":[27,29],"MEDIAN_VALUE":[40,45],"P75_VALUE":[68,61],"P90_VALUE":[72,73],"MAX_VALUE":[99,92]}}
