{"PREVALENCE_BY_GENDER_AGE_YEAR":{"TRELLIS_NAME":["40-49","50-59","70-79","40-49"],"SERIES_NAME":["MALE","FEMALE","MALE","FEMALE"],"X_CALENDAR_YEAR":[2019,2019,2019,2019],"Y_PREVALENCE_1000PP":[1.1701,1.44865,1.32903,0.85653]},"PREVALENCE_BY_MONTH":{"X_CALENDAR_MONTH":[201901,201902,201903,201905,201907,201910,201912],"Y_PREVALENCE_1000PP":[0.11,0.07,0.06,0.08,0.08,0.08,0.06]},"PROCEDURE_FREQUENCY_DISTRIBUTION":{"Y_NUM_PERSONS":[0,0,0],"X_COUNT":[1,2,3]},"PROCEDURES_BY_TYPE":{"CONCEPT_NAME":"Claim","COUNT_VALUE":97},"AGE_AT_FIRST_OCCURRENCE":{"CATEGORY":["FEMALE","MALE"],"MIN_VALUE":[0,6],"P10_VALUE":[15,15],"P25_VALUE":[28,29],"MEDIAN_VALUE":[52,46],"P75_VALUE":[60,72],"P90_VALUE":[78,75],"MAX_VALUE":[91,84]}}
