{"PREVALENCE_BY_GENDER_AGE_YEAR":{"TRELLIS_NAME":["50-59","40-49","40-49","30-39","70-79","50-59","0-9","30-39","10-19","60-69","20-29"],"SERIES_NAME":["MALE","FEMALE","MALE","MALE","FEMALE","FEMALE","FEMALE","FEMALE","MALE","FEMALE","MALE"],"X_CALENDAR_YEAR":[2019,2019,2019,2019,2019,2019,2019,2019,2019,2019,2019],"Y_PREVALENCE_1000PP":[0.88015,1.14204,1.46263,1.01678,1.6679,1.30378,1.2621,1.13969,1.83318,1.52207,1.01112]},"PREVALENCE_BY_MONTH":{"X_CALENDAR_MONTH":[201901,201903,201904,201905,201906,201907,201908,201909,201910,201911,201912],"Y_PREVALENCE_1000PP":[0.12,0.06,0.11,0.06,0.13,0.12,0.12,0.12,0.12,0.08,0.1]},"CONDITIONS_BY_TYPE":{"CONCEPT_NAME":"Claim","COUNT_VALUE":207},"AGE_AT_FIRST_DIAGNOSIS":{"CATEGORY":["FEMALE","MALE"],"MIN_VALUE":[0,1],"P10_VALUE":[12,13],"P25_VALUE":[30,22],"MEDIAN_VALUE":[52,42],"P75_VALUE":[68,57],"P90_VALUE":[77,84],"MAX_VALUE":[97,99]}}
