{"PREVALENCE_BY_GENDER_AGE_YEAR":{"TRELLIS_NAME":["40-49","30-39","40-49"],"SERIES_NAME":["FEMALE","MALE","MALE"],"X_CALENDAR_YEAR":[2019,2019,2019],"Y_PREVALENCE_1000PP":[0.99929,1.01678,1.1701]},"PREVALENCE_BY_MONTH":{"X_CALENDAR_MONTH":[201901,201904,201905,201907,201908,201909],"Y_PREVALENCE_1000PP":[0.07,0.06,0.06,0.06,0.09,0.08]},"CONDITIONS_BY_TYPE":{"CONCEPT_NAME":"Claim","COUNT_VALUE":97},"AGE_AT_FIRST_DIAGNOSIS":{"CATEGORY":["FEMALE","MALE"],"MIN_VALUE":[5,1],"P10_VALUE":[12,3],"P25_VALUE":[23,28],"MEDIAN_VALUE":[45,40],"P75_VALUE":[61,49],"P90_VALUE":[75,73],"MAX_VALUE":[91,86]}}
