{"PREVALENCE_BY_GENDER_AGE_YEAR":{"TRELLIS_NAME":["30-39","20-29","20-29","10-19","30-39","50-59","0-9","50-59","40-49","70-79","60-69","70-79","40-49","10-19"],"SERIES_NAME":["MALE","FEMALE","MALE","FEMALE","FEMALE","MALE","FEMALE","FEMALE","MALE","FEMALE","MALE","MALE","FEMALE","MALE"],"X_CALENDAR_YEAR":[2019,2019,2019,2019,2019,2019,2019,2019,2019,2019,2019,2019,2019,2019],"Y_PREVALENCE_1000PP":[1.86757,1.16822,1.17805,1.53005,0.97545,1.6148,1.47368,0.86931,1.60748,1.47956,1.54679,2.09205,1.42959,1.60698]},"PREVALENCE_BY_MONTH":{"X_CALENDAR_MONTH":[201901,201902,201904,201905,201906,201907,201908,201910,201912],"Y_PREVALENCE_1000PP":[0.18,0.15,0.25,0.08,0.1,0.23,0.08,0.17,0.09]},"PROCEDURE_FREQUENCY_DISTRIBUTION":{"Y_NUM_PERSONS":0,"X_COUNT":1},"PROCEDURES_BY_TYPE":{"CONCEPT_NAME":"Claim","COUNT_VALUE":140},"AGE_AT_FIRST_OCCURRENCE":{"CATEGORY":["FEMALE","MALE"],"MIN_VALUE":[3,1],"P10_VALUE":[9,16],"P25_VALUE":[21,34],"MEDIAN_VALUE":[43,48],"P75_VALUE":[66,66],"P90_VALUE":[75,79],"MAX_VALUE":[99,99]}}
