{"PREVALENCE_BY_GENDER_AGE_YEAR":{"TRELLIS_NAME":[],"SERIES_NAME":[],"X_CALENDAR_YEAR":[],"Y_PREVALENCE_1000PP":[]},"PREVALENCE_BY_MONTH":{"X_CALENDAR_MONTH":[201903,201905,201910],"Y_PREVALENCE_1000PP":[0.07,0.07,0.06]},"PROCEDURE_FREQUENCY_DISTRIBUTION":{"Y_NUM_PERSONS":0,"X_COUNT":4},"PROCEDURES_BY_TYPE":{"CONCEPT_NAME":"Claim","COUNT_VALUE":184},"AGE_AT_FIRST_OCCURRENCE":{"CATEGORY":["MALE","FEMALE"],"MIN_VALUE":[0,12],"P10_VALUE":[0,16],"P25_VALUE":[26,34],"MEDIAN_VALUE":[37,52],"P75_VALUE":[53,83],"P90_VALUE":[70,90],"MAX_VALUE":[78,99]}}
