{"PREVALENCE_BY_GENDER_AGE_YEAR":{"TRELLIS_NAME":["60-69","0-9","10-19","30-39","20-29","90-99","40-49","30-39","40-49","20-29","50-59","80-89","0-9","10-19","70-79","50-59","70-79","60-69"],"SERIES_NAME":["MALE","MALE","MALE","FEMALE","FEMALE","MALE","FEMALE","MALE","MALE","MALE","FEMALE","MALE","FEMALE","FEMALE","MALE","MALE","FEMALE","FEMALE"],"X_CALENDAR_YEAR":[2019,2019,2019,2019,2019,2019,2019,2019,2019,2019,2019,2019,2019,2019,2019,2019,2019,2019],"Y_PREVALENCE_1000PP":[3.28693,3.34076,4.13223,4.87726,3.33778,5.15759,2.43031,3.73514,2.19202,3.19758,3.18748,4.96963,3.15789,3.71585,4.56447,4.69759,4.80858,4.16036]},"PREVALENCE_BY_MONTH":{"X_CALENDAR_MONTH":[201901,201902,201903,201904,201905,201906,201907,201908,201909,201910,201911,201912],"Y_PREVALENCE_1000PP":[0.56,0.22,0.16,0.44,0.23,0.24,0.6,0.17,0.27,0.42,0.17,0.18]},"PROCEDURE_FREQUENCY_DISTRIBUTION":{"Y_NUM_PERSONS":0,"X_COUNT":1},"PROCEDURES_BY_TYPE":{"CONCEPT_NAME":"Claim","COUNT_VALUE":366},"AGE_AT_FIRST_OCCURRENCE":{"CATEGORY":["No matching concept","FEMALE","MALE"],"MIN_VALUE":[10,0,0],"P10_VALUE":[10,12,11],"P25_VALUE":[14,24,25],"MEDIAN_VALUE":[51,44,50],"P75_VALUE":[92,66,68],"P90_VALUE":[96,76,79],"MAX_VALUE":[96,97,97]}}
