{"PREVALENCE_BY_GENDER_AGE_YEAR":{"TRELLIS_NAME":["60-69","10-19","50-59","50-59","10-19","30-39","90-99","0-9","70-79","70-79","80-89","20-29","60-69","20-29","90-99","0-9","40-49","30-39","40-49"],"SERIES_NAME":["MALE","MALE","FEMALE","MALE","FEMALE","MALE","FEMALE","MALE","FEMALE","MALE","FEMALE","FEMALE","FEMALE","MALE","MALE","FEMALE","MALE","FEMALE","FEMALE"],"X_CALENDAR_YEAR":[2019,2019,2019,2019,2019,2019,2019,2019,2019,2019,2019,2019,2019,2019,2019,2019,2019,2019,2019],"Y_PREVALENCE_1000PP":[6.53846,4.8121,4.34594,4.40076,6.55881,5.9312,3.9019,4.45831,5.93032,5.31612,6.91643,4.82931,5.13699,4.21301,5.69801,6.52082,5.85052,5.53566,4.56817]},"PREVALENCE_BY_MONTH":{"X_CALENDAR_MONTH":[201901,201902,201903,201904,201905,201906,201907,201908,201909,201910,201911,201912],"Y_PREVALENCE_1000PP":[0.84,0.21,0.26,0.72,0.37,0.18,0.77,0.24,0.25,0.74,0.26,0.34]},"PROCEDURE_FREQUENCY_DISTRIBUTION":{"Y_NUM_PERSONS":1,"X_COUNT":4},"PROCEDURES_BY_TYPE":{"CONCEPT_NAME":"Claim","COUNT_VALUE":2072},"AGE_AT_FIRST_OCCURRENCE":{"CATEGORY":["FEMALE","MALE"],"MIN_VALUE":[0,0],"P10_VALUE":[8,12],"P25_VALUE":[20,28],"MEDIAN_VALUE":[43,44],"P75_VALUE":[62,62],"P90_VALUE":[77,77],"MAX_VALUE":[99,99]}}
