{"PREVALENCE_BY_GENDER_AGE_YEAR":{"TRELLIS_NAME":[],"SERIES_NAME":[],"X_CALENDAR_YEAR":[],"Y_PREVALENCE_1000PP":[]},"PREVALENCE_BY_MONTH":{"X_CALENDAR_MONTH":201903,"Y_PREVALENCE_1000PP":0.07},"PROCEDURE_FREQUENCY_DISTRIBUTION":{"Y_NUM_PERSONS":0,"X_COUNT":4},"PROCEDURES_BY_TYPE":{"CONCEPT_NAME":"Claim","COUNT_VALUE":164},"AGE_AT_FIRST_OCCURRENCE":{"CATEGORY":["FEMALE","MALE"],"MIN_VALUE":[11,11],"P10_VALUE":[14,12],"P25_VALUE":[35,20],"MEDIAN_VALUE":[51,50],"P75_VALUE":[79,65],"P90_VALUE":[95,88],"MAX_VALUE":[97,93]}}
