{"PREVALENCE_BY_GENDER_AGE_YEAR":{"TRELLIS_NAME":["70-79","50-59"],"SERIES_NAME":["MALE","MALE"],"X_CALENDAR_YEAR":[2019,2019],"Y_PREVALENCE_1000PP":[1.89861,1.02684]},"PREVALENCE_BY_MONTH":{"X_CALENDAR_MONTH":[201901,201906,201907,201908,201909],"Y_PREVALENCE_1000PP":[0.06,0.07,0.08,0.06,0.09]},"PROCEDURE_FREQUENCY_DISTRIBUTION":{"Y_NUM_PERSONS":0,"X_COUNT":4},"PROCEDURES_BY_TYPE":{"CONCEPT_NAME":"Claim","COUNT_VALUE":232},"AGE_AT_FIRST_OCCURRENCE":{"CATEGORY":["FEMALE","MALE"],"MIN_VALUE":[6,5],"P10_VALUE":[6,16],"P25_VALUE":[35,38],"MEDIAN_VALUE":[49,53],"P75_VALUE":[60,71],"P90_VALUE":[76,79],"MAX_VALUE":[92,95]}}
